{
  "platforms": [
    {
      "platform": "DS",
      "games": [
        {
          "name": "Metroid Prime Hunters",
          "variants": [
            {
              "print_code": "57096B",
              "satellite_code": "00001",
              "manufactured": "Japan",
              "mpn": "USA",
              "notes": ""
            },
            {
              "print_code": "57096C",
              "satellite_code": "00002",
              "manufactured": "Japan",
              "mpn": "USA",
              "notes": ""
            },
            {
              "print_code": "57102A",
              "satellite_code": "00000",
              "manufactured": "Japan",
              "mpn": "CAN",
              "notes": "French Canadian"
            },
            {
              "print_code": "57102B",
              "satellite_code": "00001",
              "manufactured": "Japan",
              "mpn": "CAN",
              "notes": "French Canadian"
            }
          ]
        }
      ]
    },
    {
      "platform": "GameCube",
      "games": [
        {
          "name": "Luigi's Mansion",
          "variants": [
            {
              "print_code": "",
              "satellite_code": "00000",
              "manufactured": "Japan",
              "mpn": "",
              "notes": "\"Uses 3 Blocks\" missing"
            },
            {
              "print_code": "",
              "satellite_code": "00000",
              "manufactured": "Japan",
              "mpn": "",
              "notes": "\"Uses 3 Blocks\" missing, French Canadian"
            },
            {
              "print_code": "",
              "satellite_code": "00100",
              "manufactured": "USA",
              "mpn": "",
              "notes": "\"Uses 3 Blocks\" corrected"
            },
            {
              "print_code": "",
              "satellite_code": "00101",
              "manufactured": "USA",
              "mpn": "",
              "notes": ""
            },
            {
              "print_code": "46179C",
              "satellite_code": "00102",
              "manufactured": "USA",
              "mpn": "",
              "notes": "Player's Choice"
            }
          ]
        },
        {
          "name": "Mario Kart Double Dash",
          "variants": [
            {
              "print_code": "52955A",
              "satellite_code": "00100",
              "manufactured": "USA",
              "mpn": "",
              "notes": ""
            },
            {
              "print_code": "53156A",
              "satellite_code": "00000",
              "manufactured": "Japan",
              "mpn": "",
              "notes": "Preorder Bonus Disc"
            }
          ]
        },
        {
          "name": "Metroid Prime",
          "variants": [
            {
              "print_code": "49689A",
              "satellite_code": "00000",
              "manufactured": "Japan",
              "mpn": "",
              "notes": ""
            },
            {
              "print_code": "49688A",
              "satellite_code": "00100",
              "manufactured": "USA",
              "mpn": "",
              "notes": ""
            },
            {
              "print_code": "49688B",
              "satellite_code": "00101",
              "manufactured": "USA",
              "mpn": "",
              "notes": "Player's Choice"
            },
            {
              "print_code": "49690A",
              "satellite_code": "00100",
              "manufactured": "USA",
              "mpn": "",
              "notes": "Best of Show E3 2002, French Canadian"
            },
            {
              "print_code": "49690B",
              "satellite_code": "00101",
              "manufactured": "USA",
              "mpn": "",
              "notes": "Player's Choice, Video Game of the Year, French Canadian"
            },
            {
              "print_code": "49692A",
              "satellite_code": "00100",
              "manufactured": "USA",
              "mpn": "",
              "notes": "NFR, K-Mart Exclusive, Wavebird Promo, front barcode"
            },
            {
              "print_code": "49830A",
              "satellite_code": "00100",
              "manufactured": "USA",
              "mpn": "",
              "notes": "Target coupons promo"
            },
            {
              "print_code": "55107A",
              "satellite_code": "00100",
              "manufactured": "USA",
              "mpn": "",
              "notes": "Metro Prime 2 Echoes bonus disc, RP-T rating"
            },
            {
              "print_code": "58069A",
              "satellite_code": "00100",
              "manufactured": "USA",
              "mpn": "",
              "notes": "NFR, Prime & Wind Waker 2-pack, E-T rating"
            }
          ]
        },
        {
          "name": "Super Smash Bros Melee",
          "variants": [
            {
              "print_code": "",
              "satellite_code": "00000",
              "manufactured": "Japan",
              "mpn": "",
              "notes": "Standard case, early Japan print start: 11/2/2001"
            },
            {
              "print_code": "",
              "satellite_code": "00000",
              "manufactured": "Japan",
              "mpn": "",
              "notes": "Security case"
            },
            {
              "print_code": "46552B",
              "satellite_code": "00001",
              "manufactured": "Japan",
              "mpn": "",
              "notes": "Best Seller"
            },
            {
              "print_code": "",
              "satellite_code": "00100",
              "manufactured": "USA",
              "mpn": "",
              "notes": "Early USA print start: 11/8/2001"
            },
            {
              "print_code": "46551B",
              "satellite_code": "00101",
              "manufactured": "USA",
              "mpn": "",
              "notes": "Player's Choice"
            },
            {
              "print_code": "46551C",
              "satellite_code": "00102",
              "manufactured": "USA",
              "mpn": "",
              "notes": "Best Seller"
            },
            {
              "print_code": "",
              "satellite_code": "00000",
              "manufactured": "Japan",
              "mpn": "",
              "notes": "NFR (front), 2002 Indigo GameCube pack-in"
            },
            {
              "print_code": "58073A",
              "satellite_code": "00100",
              "manufactured": "USA",
              "mpn": "",
              "notes": "NFR (back), 2005 Platinum  Gamecube pack-in; Cross-referenced with disc"
            },
            {
              "print_code": "58074A",
              "satellite_code": "00100",
              "manufactured": "USA",
              "mpn": "",
              "notes": "NFR (back), French Canadian"
            },
            {
              "print_code": "",
              "satellite_code": "00000",
              "manufactured": "Japan",
              "mpn": "",
              "notes": "French Canadian"
            },
            {
              "print_code": "46554B",
              "satellite_code": "00101",
              "manufactured": "USA",
              "mpn": "",
              "notes": "Player's Choice, French Canadian"
            },
            {
              "print_code": "46554C",
              "satellite_code": "00102",
              "manufactured": "USA",
              "mpn": "",
              "notes": "Best Seller, French Canadian"
            }
          ]
        },
        {
          "name": "The Legend of Zelda The Wind Waker",
          "variants": [
            {
              "print_code": "50517A",
              "satellite_code": "00000",
              "manufactured": "Japan",
              "mpn": "",
              "notes": ""
            },
            {
              "print_code": "50517B",
              "satellite_code": "00001",
              "manufactured": "Japan",
              "mpn": "",
              "notes": "Player's Choice"
            },
            {
              "print_code": "50516A",
              "satellite_code": "00100",
              "manufactured": "USA",
              "mpn": "GZLE",
              "notes": ""
            },
            {
              "print_code": "50516B",
              "satellite_code": "00101",
              "manufactured": "USA",
              "mpn": "",
              "notes": "Player's Choice"
            },
            {
              "print_code": "50955A",
              "satellite_code": "00100",
              "manufactured": "USA",
              "mpn": "YZL",
              "notes": "Rental Exclusive (e.g., blockbuster)"
            },
            {
              "print_code": "50954A",
              "satellite_code": "00100",
              "manufactured": "USA",
              "mpn": "",
              "notes": "K-Mart Exclusive"
            },
            {
              "print_code": "51061A",
              "satellite_code": "00100",
              "manufactured": "USA",
              "mpn": "YZL",
              "notes": ""
            },
            {
              "print_code": "57818A",
              "satellite_code": "00100",
              "manufactured": "USA",
              "mpn": "",
              "notes": "Player's Choice"
            },
            {
              "print_code": "51021A",
              "satellite_code": "00100",
              "manufactured": "USA",
              "mpn": "",
              "notes": "Ocarina of Time & Master Quest bonus disc, NFR"
            },
            {
              "print_code": "58069A",
              "satellite_code": "00100",
              "manufactured": "USA",
              "mpn": "",
              "notes": "NFR, Metroid Prime & Wind Waker 2-pack, E-T rating"
            },
            {
              "print_code": "57581A",
              "satellite_code": "00100",
              "manufactured": "USA",
              "mpn": "",
              "notes": "Player's Choice (French Canadian)"
            }
          ]
        }
      ]
    },
    {
      "platform": "Switch",
      "games": [
        {
          "name": "Mario Kart 8 Deluxe",
          "variants": [
            {
              "print_code": "105278A",
              "satellite_code": "00000",
              "manufactured": "USA",
              "mpn": "USA",
              "notes": ""
            },
            {
              "print_code": "105278B",
              "satellite_code": "00001",
              "manufactured": "USA",
              "mpn": "USA",
              "notes": ""
            },
            {
              "print_code": "105278C",
              "satellite_code": "00002",
              "manufactured": "USA",
              "mpn": "USA",
              "notes": "English & Spanish"
            }
          ]
        },
        {
          "name": "Super Mario Odyssey",
          "variants": [
            {
              "print_code": "105882A",
              "satellite_code": "00000",
              "manufactured": "Japan",
              "mpn": "USA",
              "notes": "English & Spanish"
            },
            {
              "print_code": "105882A",
              "satellite_code": "00001",
              "manufactured": "Japan",
              "mpn": "USA",
              "notes": "English & Spanish"
            },
            {
              "print_code": "105882C",
              "satellite_code": "00002",
              "manufactured": "Japan",
              "mpn": "USA",
              "notes": "English & Spanish"
            },
            {
              "print_code": "108795A",
              "satellite_code": "",
              "manufactured": "Japan",
              "mpn": "USZ",
              "notes": "\"Starter Pack\" box (English & Spanish)"
            },
            {
              "print_code": "108807A",
              "satellite_code": "00000",
              "manufactured": "Japan",
              "mpn": "",
              "notes": "\"Starter Pack\" pack-in, NFR (English & Spanish)"
            }
          ]
        },
        {
          "name": "Super Smash Bros Ultimate",
          "variants": [
            {
              "print_code": "108491A",
              "satellite_code": "00000",
              "manufactured": "Japan",
              "mpn": "USA",
              "notes": "English & Spanish"
            },
            {
              "print_code": "108491B",
              "satellite_code": "00001",
              "manufactured": "Japan",
              "mpn": "USA",
              "notes": "English & Spanish"
            },
            {
              "print_code": "108613A",
              "satellite_code": "",
              "manufactured": "Japan",
              "mpn": "USZ",
              "notes": "\"Ultimate Edition\" bundle (English, Spanish & French)"
            },
            {
              "print_code": "108492A",
              "satellite_code": "00000",
              "manufactured": "Japan",
              "mpn": "CAN",
              "notes": "French Canadian"
            }
          ]
        },
        {
          "name": "The Legend of Zelda Breath of the Wild",
          "variants": [
            {
              "print_code": "105211A",
              "satellite_code": "00000",
              "manufactured": "Japan",
              "mpn": "USA",
              "notes": ""
            },
            {
              "print_code": "105211B",
              "satellite_code": "00001",
              "manufactured": "Japan",
              "mpn": "USA",
              "notes": "English & Spanish ESRB (front)"
            },
            {
              "print_code": "105252A",
              "satellite_code": "00000",
              "manufactured": "Japan",
              "mpn": "USA",
              "notes": "Master Edition, Special Edition, Explorer's Edition (pack-in); no ESRB, no mpn, NFR (March 3, 2017; Explorer's Edition: Nov 23, 2017)"
            },
            {
              "print_code": "105212A",
              "satellite_code": "00000",
              "manufactured": "Japan",
              "mpn": "CAN",
              "notes": "French Canadian"
            },
            {
              "print_code": "105212B",
              "satellite_code": "00001",
              "manufactured": "Japan",
              "mpn": "CAN",
              "notes": "French Canadian"
            },
            {
              "print_code": "108492A",
              "satellite_code": "00000",
              "manufactured": "Japan",
              "mpn": "CAN",
              "notes": "French Canadian"
            }
          ]
        }
      ]
    },
    {
      "platform": "Wii",
      "games": [
        {
          "name": "Super Smash Bros Brawl",
          "variants": [
            {
              "print_code": "64279A",
              "satellite_code": "00000",
              "manufactured": "Japan",
              "mpn": "USA",
              "notes": "Wi-Fi Logo"
            },
            {
              "print_code": "64279B",
              "satellite_code": "00001",
              "manufactured": "Japan",
              "mpn": "USA",
              "notes": "No Wi-Fi logo, White ESRB"
            },
            {
              "print_code": "64278A",
              "satellite_code": "00100",
              "manufactured": "USA",
              "mpn": "USA",
              "notes": "Wi-Fi logo"
            },
            {
              "print_code": "64278B",
              "satellite_code": "00101",
              "manufactured": "USA",
              "mpn": "USA",
              "notes": "Wi-Fi logo, Fighting Game of the Year"
            },
            {
              "print_code": "64278C",
              "satellite_code": "00102",
              "manufactured": "USA",
              "mpn": "USA",
              "notes": "Wi-Fi logo"
            },
            {
              "print_code": "64278D",
              "satellite_code": "00103",
              "manufactured": "USA",
              "mpn": "USA",
              "notes": "No Wi-Fi logo, White ESRB"
            },
            {
              "print_code": "77615A",
              "satellite_code": "00100",
              "manufactured": "USA",
              "mpn": "USA",
              "notes": "Wi-Fi logo"
            },
            {
              "print_code": "77615B",
              "satellite_code": "00101",
              "manufactured": "USA",
              "mpn": "USA",
              "notes": "No Wi-Fi logo, White ESRB"
            },
            {
              "print_code": "65591A",
              "satellite_code": "00100",
              "manufactured": "USA",
              "mpn": "CAN",
              "notes": "Wi-Fi logo"
            },
            {
              "print_code": "65591B",
              "satellite_code": "00101",
              "manufactured": "USA",
              "mpn": "CAN",
              "notes": "Wi-Fi logo"
            }
          ]
        }
      ]
    },
    {
      "platform": "Wii U",
      "games": [
        {
          "name": "Bayonetta 2",
          "variants": [
            {
              "print_code": "83663A",
              "satellite_code": "00000",
              "manufactured": "USA",
              "mpn": "USZ",
              "notes": "satellite_code error, includes Bayonetta 1"
            },
            {
              "print_code": "83663B",
              "satellite_code": "00100",
              "manufactured": "USA",
              "mpn": "USZ",
              "notes": "Includes Bayonetta 1"
            },
            {
              "print_code": "100178A",
              "satellite_code": "00100",
              "manufactured": "USA",
              "mpn": "USZ",
              "notes": "Includes Bayonetta 1"
            },
            {
              "print_code": "103567A",
              "satellite_code": "00000",
              "manufactured": "Japan",
              "mpn": "USZ",
              "notes": ""
            }
          ]
        },
        {
          "name": "Mario Kart 8",
          "variants": [
            {
              "print_code": "82909A",
              "satellite_code": "00100",
              "manufactured": "USA",
              "mpn": "USZ",
              "notes": "Nintendo Network badge"
            },
            {
              "print_code": "82909B",
              "satellite_code": "00101",
              "manufactured": "USA",
              "mpn": "USZ",
              "notes": "Nintendo Network badge"
            },
            {
              "print_code": "83055A",
              "satellite_code": "00100",
              "manufactured": "USA",
              "mpn": "USZ",
              "notes": "Nintendo Network badge, NFR (2014 Wii U 32GB + Mario Kart 8 \"Deluxe Set\")"
            },
            {
              "print_code": "101514A",
              "satellite_code": "00100",
              "manufactured": "USA",
              "mpn": "USZ",
              "notes": "\"amiibo\" badge, \"amiibo\" no TM"
            },
            {
              "print_code": "101979A",
              "satellite_code": "00000",
              "manufactured": "Japan",
              "mpn": "USZ",
              "notes": "\"amiibo\" badge, \"amiibo\" with TM"
            }
          ]
        },
        {
          "name": "Super Mario 3D World",
          "variants": [
            {
              "print_code": "81224A",
              "satellite_code": "00100",
              "manufactured": "USA",
              "mpn": "USZ",
              "notes": "English, French & Spanish"
            },
            {
              "print_code": "81224C",
              "satellite_code": "00102",
              "manufactured": "USA",
              "mpn": "USZ",
              "notes": "Red Case, Family Game of the Year Badge (English, French & Spanish)"
            },
            {
              "print_code": "101973A",
              "satellite_code": "00000",
              "manufactured": "Japan",
              "mpn": "USZ",
              "notes": "Red Case (English, French & Spanish)"
            },
            {
              "print_code": "100420A",
              "satellite_code": "00100",
              "manufactured": "USA",
              "mpn": "USZ",
              "notes": "Red Case, NFR (English, French & Spanish)"
            },
            {
              "print_code": "103634A",
              "satellite_code": "00000",
              "manufactured": "Japan",
              "mpn": "USZ",
              "notes": "Nintendo Selects (English, French & Spanish)"
            }
          ]
        },
        {
          "name": "Super Smash Bros For Wii U",
          "variants": [
            {
              "print_code": "83664A",
              "satellite_code": "00100",
              "manufactured": "USA",
              "mpn": "USZ",
              "notes": ""
            },
            {
              "print_code": "100201A",
              "satellite_code": "N/A",
              "manufactured": "USA",
              "mpn": "USA",
              "notes": "Controller w/ Adapter bundle box, limited edition first print"
            },
            {
              "print_code": "83665A",
              "satellite_code": "00100",
              "manufactured": "USA",
              "mpn": "N/A",
              "notes": "Controller w/ Adapter bundle pack-in, NFR, first print"
            },
            {
              "print_code": "101842A",
              "satellite_code": "00100",
              "manufactured": "USA",
              "mpn": "USZ",
              "notes": "\"Read/Write\" text"
            },
            {
              "print_code": "101986A",
              "satellite_code": "00000",
              "manufactured": "Japan",
              "mpn": "USZ",
              "notes": "\"Read/Write\" text"
            },
            {
              "print_code": "101986B",
              "satellite_code": "00001",
              "manufactured": "Japan",
              "mpn": "USZ",
              "notes": "\"Read/Write\" text"
            },
            {
              "print_code": "101986C",
              "satellite_code": "00002",
              "manufactured": "Japan",
              "mpn": "USZ",
              "notes": "\"Read/Write\" text"
            }
          ]
        }
      ]
    },
    {
      "platform": "Xbox 360",
      "games": [
        {
          "name": "Dishonored",
          "variants": [
            {
              "print_code": "793WR",
              "satellite_code": "",
              "manufactured": "",
              "mpn": "",
              "notes": "2012, Made in Mexico sticker"
            },
            {
              "print_code": "793WR",
              "satellite_code": "",
              "manufactured": "",
              "mpn": "",
              "notes": "2012, Made in Mexico stamp"
            },
            {
              "print_code": "892WR",
              "satellite_code": "",
              "manufactured": "",
              "mpn": "",
              "notes": "2013, Slip cover, Game of the Year Edition"
            }
          ]
        }
      ]
    }
  ]
}
